weaviate_orm/__init__.py
weaviate_orm/weaviate_base.py
weaviate_orm/weaviate_decorators.py
weaviate_orm/weaviate_engine.py
weaviate_orm/weaviate_meta.py
weaviate_orm/weaviate_property.py
weaviate_orm/weaviate_utility.py
weaviate_orm/weavitae_reference.py
weaviate_orm-0.1.15.dist-info/licenses/LICENSE
weaviate_orm-0.1.15.dist-info/METADATA
weaviate_orm-0.1.15.dist-info/WHEEL
weaviate_orm-0.1.15.dist-info/top_level.txt
weaviate_orm-0.1.15.dist-info/RECORD
