Metadata-Version: 2.4
Name: weaviate-orm
Version: 0.1.15
Summary: A lightweight ORM-style layer for Weaviate
Author-email: Tobias Heimig-Elschner <Tobias.Heimig-Elschner@bbr.bund.de>
License-Expression: GPL-3.0-or-later
Project-URL: Homepage, https://gitlab.opencode.de/bbsr_ida_public/weaviate_orm
Project-URL: Issues, https://gitlab.opencode.de/bbsr_ida_public/weaviate_orm/-/issues
Project-URL: Citation, https://doi.org/10.58007/x1wa-rt92
Classifier: Programming Language :: Python :: 3
Classifier: Operating System :: OS Independent
Requires-Python: >=3.11
License-File: LICENSE
Requires-Dist: weaviate-client>=4.16.0
Dynamic: license-file
